{
  "id": "calculus-full-demo",
  "title": "Calculus Demonstration Set",
  "questions": [
    {
      "id": "q1",
      "text": "Differentiate \\(y = 3x^2 + 5x\\).",
      "topic": "Calculus",
      "marks": 3,
      "hint": "Use the power rule."
    },
    {
      "id": "q2",
      "text": "Find the derivative of \\(f(x) = \\sin(x) + e^x\\).",
      "topic": "Calculus",
      "marks": 4,
      "hint": "Differentiate each term separately using standard trigonometric and exponential rules."
    },
    {
      "id": "q3",
      "text": "Evaluate the indefinite integral \\(\\int (4x^3 - 2x) \\, dx\\).",
      "topic": "Calculus",
      "marks": 4,
      "hint": "Apply the reverse power rule and don't forget the constant of integration."
    },
    {
      "id": "q4",
      "text": "Find the equation of the tangent line to the curve \\(y = x^3 - 2x^2 + 4\\) at the point where \\(x = 2\\).",
      "topic": "Calculus",
      "marks": 6,
      "hint": "First, find the derivative \\(\\frac{dy}{dx}\\) to determine the gradient function. Substitute \\(x = 2\\) to find the specific gradient and the corresponding \\(y\\)-value, then use the point-slope form to write the equation."
    }
  ]
}